{
  "main": {
    "id": "7bf713fe15587e9f",
    "type": "split",
    "children": [
      {
        "id": "c94ae1d9b092739f",
        "type": "tabs",
        "children": [
          {
            "id": "a6fadc064bdd4a94",
            "type": "leaf",
            "state": {
              "type": "graph",
              "state": {},
              "icon": "lucide-git-fork",
              "title": "Graph view"
            }
          },
          {
            "id": "271e1160572b201a",
            "type": "leaf",
            "state": {
              "type": "markdown",
              "state": {
                "file": "Development/Developer notes.md",
                "mode": "source",
                "source": false
              },
              "icon": "lucide-file",
              "title": "Developer notes"
            }
          },
          {
            "id": "8a47fbf9cfce69a7",
            "type": "leaf",
            "state": {
              "type": "markdown",
              "state": {
                "file": "Core Concepts/Player Characters.md",
                "mode": "source",
                "source": false
              },
              "icon": "lucide-file",
              "title": "Player Characters"
            }
          },
          {
            "id": "e2a1da3be087de18",
            "type": "leaf",
            "state": {
              "type": "markdown",
              "state": {
                "file": "Development/Test Characters.md",
                "mode": "source",
                "source": false
              },
              "icon": "lucide-file",
              "title": "Test Characters"
            }
          },
          {
            "id": "964fc5003e9f95bb",
            "type": "leaf",
            "state": {
              "type": "markdown",
              "state": {
                "file": "Classes/Spellslinger.md",
                "mode": "source",
                "source": false
              },
              "icon": "lucide-file",
              "title": "Spellslinger"
            }
          }
        ],
        "currentTab": 1
      },
      {
        "id": "8e37846b47c4e3c8",
        "type": "tabs",
        "children": [
          {
            "id": "011f629e796b9d12",
            "type": "leaf",
            "state": {
              "type": "markdown",
              "state": {
                "file": "Classes/Witch.md",
                "mode": "source",
                "source": false
              },
              "icon": "lucide-file",
              "title": "Witch"
            }
          },
          {
            "id": "86c38ad5b213ea4f",
            "type": "leaf",
            "state": {
              "type": "markdown",
              "state": {
                "file": "Stats/AP.md",
                "mode": "source",
                "source": false
              },
              "icon": "lucide-file",
              "title": "AP"
            }
          },
          {
            "id": "5dbfdc471cf4594e",
            "type": "leaf",
            "state": {
              "type": "markdown",
              "state": {
                "file": "Core Concepts/Damage Types.md",
                "mode": "source",
                "source": false
              },
              "icon": "lucide-file",
              "title": "Damage Types"
            }
          },
          {
            "id": "d2fe7af0603a8043",
            "type": "leaf",
            "state": {
              "type": "markdown",
              "state": {
                "file": "Classes/Trapper.md",
                "mode": "source",
                "source": false
              },
              "icon": "lucide-file",
              "title": "Trapper"
            }
          },
          {
            "id": "749a128accdf7496",
            "type": "leaf",
            "state": {
              "type": "markdown",
              "state": {
                "file": "Stats/Criticals.md",
                "mode": "source",
                "source": false
              },
              "icon": "lucide-file",
              "title": "Criticals"
            }
          }
        ],
        "currentTab": 3
      }
    ],
    "direction": "vertical"
  },
  "left": {
    "id": "068c9effe2d71b9a",
    "type": "split",
    "children": [
      {
        "id": "617252b5e73e434b",
        "type": "tabs",
        "children": [
          {
            "id": "8317809c0fa4d756",
            "type": "leaf",
            "state": {
              "type": "file-explorer",
              "state": {
                "sortOrder": "alphabetical",
                "autoReveal": false
              },
              "icon": "lucide-folder-closed",
              "title": "Files"
            }
          },
          {
            "id": "b75de7821adcaa74",
            "type": "leaf",
            "state": {
              "type": "search",
              "state": {
                "query": "",
                "matchingCase": false,
                "explainSearch": false,
                "collapseAll": false,
                "extraContext": false,
                "sortOrder": "alphabetical"
              },
              "icon": "lucide-search",
              "title": "Search"
            }
          },
          {
            "id": "90a81dc6dfcc375e",
            "type": "leaf",
            "state": {
              "type": "bookmarks",
              "state": {},
              "icon": "lucide-bookmark",
              "title": "Bookmarks"
            }
          }
        ]
      }
    ],
    "direction": "horizontal",
    "width": 300
  },
  "right": {
    "id": "2d56044ac206b702",
    "type": "split",
    "children": [
      {
        "id": "c925f67f536d26ff",
        "type": "tabs",
        "children": [
          {
            "id": "3dfab03e463dbbdf",
            "type": "leaf",
            "state": {
              "type": "backlink",
              "state": {
                "file": "Skillsets and Species/Knight.md",
                "collapseAll": false,
                "extraContext": false,
                "sortOrder": "alphabetical",
                "showSearch": false,
                "searchQuery": "",
                "backlinkCollapsed": false,
                "unlinkedCollapsed": true
              },
              "icon": "links-coming-in",
              "title": "Backlinks for Knight"
            }
          },
          {
            "id": "bc8c5fb8f52a0ccf",
            "type": "leaf",
            "state": {
              "type": "outgoing-link",
              "state": {
                "linksCollapsed": false,
                "unlinkedCollapsed": true
              },
              "icon": "links-going-out",
              "title": "Outgoing links"
            }
          },
          {
            "id": "bc0bacbcfde53acd",
            "type": "leaf",
            "state": {
              "type": "tag",
              "state": {
                "sortOrder": "frequency",
                "useHierarchy": true,
                "showSearch": false,
                "searchQuery": ""
              },
              "icon": "lucide-tags",
              "title": "Tags"
            }
          },
          {
            "id": "c29bad89f6a91294",
            "type": "leaf",
            "state": {
              "type": "outline",
              "state": {
                "followCursor": false,
                "showSearch": false,
                "searchQuery": ""
              },
              "icon": "lucide-list",
              "title": "Outline"
            }
          }
        ]
      }
    ],
    "direction": "horizontal",
    "width": 300,
    "collapsed": true
  },
  "left-ribbon": {
    "hiddenItems": {
      "switcher:Open quick switcher": false,
      "graph:Open graph view": false,
      "canvas:Create new canvas": false,
      "daily-notes:Open today's daily note": false,
      "templates:Insert template": false,
      "command-palette:Open command palette": false
    }
  },
  "active": "271e1160572b201a",
  "lastOpenFiles": [
    "Classes/Spellslinger.md",
    "Classes/Trapper.md",
    "Classes/Soldier.md",
    "Stats/Criticals.md",
    "Classes/Knight.md",
    "Classes/Dancer.md",
    "Classes/Trickster.md",
    "Core Concepts/Damage Types.md",
    "Core Concepts/Status Effects.md",
    "Sets/Weapons/Hammers.md",
    "Core Concepts/Weapons.md",
    "Classes/Witch.md",
    "Sets/Weapons/Axes.md",
    "Stats/EP.md",
    "Stats/AP.md",
    "Development/Developer notes.md",
    "Sets/Miscellaneous/Implants.md",
    "Sets/Miscellaneous/Jewellery.md",
    "Core Concepts/Miscellaneous.md",
    "Core Concepts/Non-Combat.md",
    "Classes/Doctor.md",
    "Development/Test Characters.md",
    "Core Concepts/Combat.md",
    "Sets/Miscellaneous/Shoes.md",
    "Core Concepts/Player Characters.md",
    "Structure/Welcome.md",
    "Pasted image 20250628201830.png",
    "Sets/Miscellaneous",
    "Sets/Creatures",
    "Sets/Armours",
    "Sets/Attachments",
    "Sets/Spells",
    "Sets/Ammunition",
    "Sets/Weapons",
    "Pasted image 20250626202807.png",
    "Species",
    "Development",
    "Resources/Ehlen Map Resource.png",
    "Resources"
  ]
}